{
  "pagename":"testpage.json",
  "elements":[
    {"name":"name1","waitTime":"0","type":"id","value":"myid","NextPage":"np","showMode":"mode","defaultValue":"dvalue","textContent":"t"},
    {"name":"name2","waitTime":"0","type":"id","value":"myid","NextPage":"np","showMode":"mode","defaultValue":"dvalue","textContent":"t"},
    {"name":"name3","waitTime":"0","type":"id","value":"myid","NextPage":"np","showMode":"mode","defaultValue":"dvalue","textContent":"t"},
    {"name":"name4","waitTime":"0","type":"id","value":"myid2","NextPage":"np","showMode":"mode","defaultValue":"dvalue","textContent":"t"},
    {"name":"name5","waitTime":"0","type":"id","value":"myid2","NextPage":"np","showMode":"mode","defaultValue":"dvalue","textContent":"t"},
    {"name":"name6","waitTime":"0","type":"id","value":"myid2","NextPage":"np","showMode":"mode","defaultValue":"dvalue","textContent":"t"},
    {"name":"name7","waitTime":"0","type":"id","value":"myid2","NextPage":"np","showMode":"mode","defaultValue":"dvalue","textContent":"t"},
    {"name":"name8","waitTime":"0","type":"id","value":"myid2","NextPage":"np","showMode":"mode","defaultValue":"dvalue","textContent":"t"},
    {"name":"name9","waitTime":"0","type":"id","value":"myid2","NextPage":"np","showMode":"mode","defaultValue":"dvalue","textContent":"t"},
    {"name":"name10","waitTime":"0","type":"id","value":"myid2","NextPage":"np","showMode":"mode","defaultValue":"dvalue","textContent":"t"},
    {"name":"name11","waitTime":"0","type":"id","value":"myid2","NextPage":"np","showMode":"mode","defaultValue":"dvalue","textContent":"t"},
    {"name":"name12","waitTime":"0","type":"id","value":"myid2","NextPage":"np","showMode":"mode","defaultValue":"dvalue","textContent":"t"},
    {"name":"name13","waitTime":"0","type":"id","value":"myid2","NextPage":"np","showMode":"mode","defaultValue":"dvalue","textContent":"t"},
    {"name":"name14","waitTime":"0","type":"id","value":"myid2","NextPage":"np","showMode":"mode","defaultValue":"dvalue","textContent":"t"},
    {"name":"name15","waitTime":"0","type":"id","value":"myid2","NextPage":"np","showMode":"mode","defaultValue":"dvalue","textContent":"t"},
    {"name":"name16","waitTime":"0","type":"id","value":"myid2","NextPage":"np","showMode":"mode","defaultValue":"dvalue","textContent":"t"},
    {"name":"name17","waitTime":"0","type":"id","value":"myid2","NextPage":"np","showMode":"mode","defaultValue":"dvalue","textContent":"t"},
    {"name":"name18","waitTime":"0","type":"id","value":"myid2","NextPage":"np","showMode":"mode","defaultValue":"dvalue","textContent":"t"},
    {"name":"name19","waitTime":"0","type":"id","value":"myid2","NextPage":"np","showMode":"mode","defaultValue":"dvalue","textContent":"t"},
    {"name":"name20","waitTime":"0","type":"id","value":"myid2","NextPage":"np","showMode":"mode","defaultValue":"dvalue","textContent":"t"},
    {"name":"name21","waitTime":"0","type":"id","value":"myid2","NextPage":"np","showMode":"mode","defaultValue":"dvalue","textContent":"t"},
    {"name":"name22","waitTime":"0","type":"id","value":"myid2","NextPage":"np","showMode":"mode","defaultValue":"dvalue","textContent":"t"},
    {"name":"name1","waitTime":"0","type":"id","value":"myid","NextPage":"np","showMode":"mode","defaultValue":"dvalue","textContent":"t"},
    {"name":"name1","waitTime":"0","type":"id","value":"myid","NextPage":"np","showMode":"mode","defaultValue":"dvalue","textContent":"t"},
    {"name":"name1","waitTime":"0","type":"id","value":"myid","NextPage":"np","showMode":"mode","defaultValue":"dvalue","textContent":"t"},
    {"name":"name1","waitTime":"0","type":"id","value":"myid","NextPage":"np","showMode":"mode","defaultValue":"dvalue","textContent":"t"},
    {"name":"name1","waitTime":"0","type":"id","value":"myid","NextPage":"np","showMode":"mode","defaultValue":"dvalue","textContent":"t"},
    {"name":"name1","waitTime":"0","type":"id","value":"myid","NextPage":"np","showMode":"mode","defaultValue":"dvalue","textContent":"t"},
    {"name":"name1","waitTime":"0","type":"id","value":"myid","NextPage":"np","showMode":"mode","defaultValue":"dvalue","textContent":"t"},
    {"name":"name1","waitTime":"0","type":"id","value":"myid","NextPage":"np","showMode":"mode","defaultValue":"dvalue","textContent":"t"},
    {"name":"name1","waitTime":"0","type":"id","value":"myid","NextPage":"np","showMode":"mode","defaultValue":"dvalue","textContent":"t"},
    {"name":"name1","waitTime":"0","type":"id","value":"myid","NextPage":"np","showMode":"mode","defaultValue":"dvalue","textContent":"t"},
    {"name":"name1","waitTime":"0","type":"id","value":"myid","NextPage":"np","showMode":"mode","defaultValue":"dvalue","textContent":"t"},
    {"name":"name1","waitTime":"0","type":"id","value":"myid","NextPage":"np","showMode":"mode","defaultValue":"dvalue","textContent":"t"},
    {"name":"name1","waitTime":"0","type":"id","value":"myid","NextPage":"np","showMode":"mode","defaultValue":"dvalue","textContent":"t"},
    {"name":"name1","waitTime":"0","type":"id","value":"myid","NextPage":"np","showMode":"mode","defaultValue":"dvalue","textContent":"t"},
    {"name":"name1","waitTime":"0","type":"id","value":"myid","NextPage":"np","showMode":"mode","defaultValue":"dvalue","textContent":"t"},
    {"name":"name1","waitTime":"0","type":"id","value":"myid","NextPage":"np","showMode":"mode","defaultValue":"dvalue","textContent":"t"},
    {"name":"name1","waitTime":"0","type":"id","value":"myid","NextPage":"np","showMode":"mode","defaultValue":"dvalue","textContent":"t"},
    {"name":"name1","waitTime":"0","type":"id","value":"myid","NextPage":"np","showMode":"mode","defaultValue":"dvalue","textContent":"t"},
    {"name":"name1","waitTime":"0","type":"id","value":"myid","NextPage":"np","showMode":"mode","defaultValue":"dvalue","textContent":"t"},
    {"name":"name1","waitTime":"0","type":"id","value":"myid","NextPage":"np","showMode":"mode","defaultValue":"dvalue","textContent":"t"},
    {"name":"name1","waitTime":"0","type":"id","value":"myid","NextPage":"np","showMode":"mode","defaultValue":"dvalue","textContent":"t"},
    {"name":"name1","waitTime":"0","type":"id","value":"myid","NextPage":"np","showMode":"mode","defaultValue":"dvalue","textContent":"t"},
    {"name":"name1","waitTime":"0","type":"id","value":"myid","NextPage":"np","showMode":"mode","defaultValue":"dvalue","textContent":"t"},
    {"name":"name1","waitTime":"0","type":"id","value":"myid","NextPage":"np","showMode":"mode","defaultValue":"dvalue","textContent":"t"},
    {"name":"name1","waitTime":"0","type":"id","value":"myid","NextPage":"np","showMode":"mode","defaultValue":"dvalue","textContent":"t"},
    {"name":"name1","waitTime":"0","type":"id","value":"myid","NextPage":"np","showMode":"mode","defaultValue":"dvalue","textContent":"t"},
    {"name":"name1","waitTime":"0","type":"id","value":"myid","NextPage":"np","showMode":"mode","defaultValue":"dvalue","textContent":"t"},
    {"name":"name1","waitTime":"0","type":"id","value":"myid","NextPage":"np","showMode":"mode","defaultValue":"dvalue","textContent":"t"},
    {"name":"name1","waitTime":"0","type":"id","value":"myid","NextPage":"np","showMode":"mode","defaultValue":"dvalue","textContent":"t"},
    {"name":"name1","waitTime":"0","type":"id","value":"myid","NextPage":"np","showMode":"mode","defaultValue":"dvalue","textContent":"t"},
    {"name":"name1","waitTime":"0","type":"id","value":"myid","NextPage":"np","showMode":"mode","defaultValue":"dvalue","textContent":"t"},
    {"name":"name1","waitTime":"0","type":"id","value":"myid","NextPage":"np","showMode":"mode","defaultValue":"dvalue","textContent":"t"},
    {"name":"name1","waitTime":"0","type":"id","value":"myid","NextPage":"np","showMode":"mode","defaultValue":"dvalue","textContent":"t"},
    {"name":"name1","waitTime":"0","type":"id","value":"myid","NextPage":"np","showMode":"mode","defaultValue":"dvalue","textContent":"t"},
    {"name":"name1","waitTime":"0","type":"id","value":"myid","NextPage":"np","showMode":"mode","defaultValue":"dvalue","textContent":"t"},
    {"name":"name1","waitTime":"0","type":"id","value":"myid","NextPage":"np","showMode":"mode","defaultValue":"dvalue","textContent":"t"},
    {"name":"name1","waitTime":"0","type":"id","value":"myid","NextPage":"np","showMode":"mode","defaultValue":"dvalue","textContent":"t"},
    {"name":"name1","waitTime":"0","type":"id","value":"myid","NextPage":"np","showMode":"mode","defaultValue":"dvalue","textContent":"t"},
    {"name":"name1","waitTime":"0","type":"id","value":"myid","NextPage":"np","showMode":"mode","defaultValue":"dvalue","textContent":"t"},
    {"name":"name1","waitTime":"0","type":"id","value":"myid","NextPage":"np","showMode":"mode","defaultValue":"dvalue","textContent":"t"},
    {"name":"name1","waitTime":"0","type":"id","value":"myid","NextPage":"np","showMode":"mode","defaultValue":"dvalue","textContent":"t"},
    {"name":"name1","waitTime":"0","type":"id","value":"myid","NextPage":"np","showMode":"mode","defaultValue":"dvalue","textContent":"t"},
    {"name":"name1","waitTime":"0","type":"id","value":"myid","NextPage":"np","showMode":"mode","defaultValue":"dvalue","textContent":"t"},
    {"name":"name1","waitTime":"0","type":"id","value":"myid","NextPage":"np","showMode":"mode","defaultValue":"dvalue","textContent":"t"},
    {"name":"name1","waitTime":"0","type":"id","value":"myid","NextPage":"np","showMode":"mode","defaultValue":"dvalue","textContent":"t"},
    {"name":"name1","waitTime":"0","type":"id","value":"myid","NextPage":"np","showMode":"mode","defaultValue":"dvalue","textContent":"t"},
    {"name":"name1","waitTime":"0","type":"id","value":"myid","NextPage":"np","showMode":"mode","defaultValue":"dvalue","textContent":"t"},
    {"name":"name1","waitTime":"0","type":"id","value":"myid","NextPage":"np","showMode":"mode","defaultValue":"dvalue","textContent":"t"},
    {"name":"name1","waitTime":"0","type":"id","value":"myid","NextPage":"np","showMode":"mode","defaultValue":"dvalue","textContent":"t"},
    {"name":"name1","waitTime":"0","type":"id","value":"myid","NextPage":"np","showMode":"mode","defaultValue":"dvalue","textContent":"t"},
    {"name":"name1","waitTime":"0","type":"id","value":"myid","NextPage":"np","showMode":"mode","defaultValue":"dvalue","textContent":"t"},
    {"name":"name1","waitTime":"0","type":"id","value":"myid","NextPage":"np","showMode":"mode","defaultValue":"dvalue","textContent":"t"},
    {"name":"name1","waitTime":"0","type":"id","value":"myid","NextPage":"np","showMode":"mode","defaultValue":"dvalue","textContent":"t"},
    {"name":"name1","waitTime":"0","type":"id","value":"myid","NextPage":"np","showMode":"mode","defaultValue":"dvalue","textContent":"t"},
    {"name":"name1","waitTime":"0","type":"id","value":"myid","NextPage":"np","showMode":"mode","defaultValue":"dvalue","textContent":"t"},
    {"name":"name1","waitTime":"0","type":"id","value":"myid","NextPage":"np","showMode":"mode","defaultValue":"dvalue","textContent":"t"},
    {"name":"name1","waitTime":"0","type":"id","value":"myid","NextPage":"np","showMode":"mode","defaultValue":"dvalue","textContent":"t"},
    {"name":"name1","waitTime":"0","type":"id","value":"myid","NextPage":"np","showMode":"mode","defaultValue":"dvalue","textContent":"t"},
    {"name":"name1","waitTime":"0","type":"id","value":"myid","NextPage":"np","showMode":"mode","defaultValue":"dvalue","textContent":"t"},
    {"name":"name1","waitTime":"0","type":"id","value":"myid","NextPage":"np","showMode":"mode","defaultValue":"dvalue","textContent":"t"},
    {"name":"name1","waitTime":"0","type":"id","value":"myid","NextPage":"np","showMode":"mode","defaultValue":"dvalue","textContent":"t"},
    {"name":"name1","waitTime":"0","type":"id","value":"myid","NextPage":"np","showMode":"mode","defaultValue":"dvalue","textContent":"t"},
    {"name":"name1","waitTime":"0","type":"id","value":"myid","NextPage":"np","showMode":"mode","defaultValue":"dvalue","textContent":"t"},
    {"name":"name1","waitTime":"0","type":"id","value":"myid","NextPage":"np","showMode":"mode","defaultValue":"dvalue","textContent":"t"},
    {"name":"name1","waitTime":"0","type":"id","value":"myid","NextPage":"np","showMode":"mode","defaultValue":"dvalue","textContent":"t"},
    {"name":"name1","waitTime":"0","type":"id","value":"myid","NextPage":"np","showMode":"mode","defaultValue":"dvalue","textContent":"t"},
    {"name":"name1","waitTime":"0","type":"id","value":"myid","NextPage":"np","showMode":"mode","defaultValue":"dvalue","textContent":"t"},
    {"name":"name1","waitTime":"0","type":"id","value":"myid","NextPage":"np","showMode":"mode","defaultValue":"dvalue","textContent":"t"},
    {"name":"name1","waitTime":"0","type":"id","value":"myid","NextPage":"np","showMode":"mode","defaultValue":"dvalue","textContent":"t"},
    {"name":"name1","waitTime":"0","type":"id","value":"myid","NextPage":"np","showMode":"mode","defaultValue":"dvalue","textContent":"t"},
    {"name":"name1","waitTime":"0","type":"id","value":"myid","NextPage":"np","showMode":"mode","defaultValue":"dvalue","textContent":"t"},
    {"name":"name1","waitTime":"0","type":"id","value":"myid","NextPage":"np","showMode":"mode","defaultValue":"dvalue","textContent":"t"},
    {"name":"name1","waitTime":"0","type":"id","value":"myid","NextPage":"np","showMode":"mode","defaultValue":"dvalue","textContent":"t"},
    {"name":"name1","waitTime":"0","type":"id","value":"myid","NextPage":"np","showMode":"mode","defaultValue":"dvalue","textContent":"t"},
    {"name":"name1","waitTime":"0","type":"id","value":"myid","NextPage":"np","showMode":"mode","defaultValue":"dvalue","textContent":"t"},
    {"name":"name1","waitTime":"0","type":"id","value":"myid","NextPage":"np","showMode":"mode","defaultValue":"dvalue","textContent":"t"},
    {"name":"name1","waitTime":"0","type":"id","value":"myid","NextPage":"np","showMode":"mode","defaultValue":"dvalue","textContent":"t"},
    {"name":"name1","waitTime":"0","type":"id","value":"myid","NextPage":"np","showMode":"mode","defaultValue":"dvalue","textContent":"t"},
    {"name":"name1","waitTime":"0","type":"id","value":"myid","NextPage":"np","showMode":"mode","defaultValue":"dvalue","textContent":"t"},
    {"name":"name1","waitTime":"0","type":"id","value":"myid","NextPage":"np","showMode":"mode","defaultValue":"dvalue","textContent":"t"},
    {"name":"name1","waitTime":"0","type":"id","value":"myid","NextPage":"np","showMode":"mode","defaultValue":"dvalue","textContent":"t"},
    {"name":"name1","waitTime":"0","type":"id","value":"myid","NextPage":"np","showMode":"mode","defaultValue":"dvalue","textContent":"t"},
    {"name":"name1","waitTime":"0","type":"id","value":"myid","NextPage":"np","showMode":"mode","defaultValue":"dvalue","textContent":"t"},
    {"name":"name1","waitTime":"0","type":"id","value":"myid","NextPage":"np","showMode":"mode","defaultValue":"dvalue","textContent":"t"},
    {"name":"name1","waitTime":"0","type":"id","value":"myid","NextPage":"np","showMode":"mode","defaultValue":"dvalue","textContent":"t"},
    {"name":"name1","waitTime":"0","type":"id","value":"myid","NextPage":"np","showMode":"mode","defaultValue":"dvalue","textContent":"t"},
    {"name":"name1","waitTime":"0","type":"id","value":"myid","NextPage":"np","showMode":"mode","defaultValue":"dvalue","textContent":"t"},
    {"name":"name1","waitTime":"0","type":"id","value":"myid","NextPage":"np","showMode":"mode","defaultValue":"dvalue","textContent":"t"},
    {"name":"name1","waitTime":"0","type":"id","value":"myid","NextPage":"np","showMode":"mode","defaultValue":"dvalue","textContent":"t"},
    {"name":"name1","waitTime":"0","type":"id","value":"myid","NextPage":"np","showMode":"mode","defaultValue":"dvalue","textContent":"t"},
    {"name":"name1","waitTime":"0","type":"id","value":"myid","NextPage":"np","showMode":"mode","defaultValue":"dvalue","textContent":"t"},
    {"name":"name1","waitTime":"0","type":"id","value":"myid","NextPage":"np","showMode":"mode","defaultValue":"dvalue","textContent":"t"},
    {"name":"name1","waitTime":"0","type":"id","value":"myid","NextPage":"np","showMode":"mode","defaultValue":"dvalue","textContent":"t"},
    {"name":"name1","waitTime":"0","type":"id","value":"myid","NextPage":"np","showMode":"mode","defaultValue":"dvalue","textContent":"t"},
    {"name":"name1","waitTime":"0","type":"id","value":"myid","NextPage":"np","showMode":"mode","defaultValue":"dvalue","textContent":"t"},
    {"name":"name1","waitTime":"0","type":"id","value":"myid","NextPage":"np","showMode":"mode","defaultValue":"dvalue","textContent":"t"},
    {"name":"name1","waitTime":"0","type":"id","value":"myid","NextPage":"np","showMode":"mode","defaultValue":"dvalue","textContent":"t"},
    {"name":"name1","waitTime":"0","type":"id","value":"myid","NextPage":"np","showMode":"mode","defaultValue":"dvalue","textContent":"t"},
    {"name":"name1","waitTime":"0","type":"id","value":"myid","NextPage":"np","showMode":"mode","defaultValue":"dvalue","textContent":"t"},
    {"name":"name1","waitTime":"0","type":"id","value":"myid","NextPage":"np","showMode":"mode","defaultValue":"dvalue","textContent":"t"},
    {"name":"name1","waitTime":"0","type":"id","value":"myid","NextPage":"np","showMode":"mode","defaultValue":"dvalue","textContent":"t"},
    {"name":"name1","waitTime":"0","type":"id","value":"myid","NextPage":"np","showMode":"mode","defaultValue":"dvalue","textContent":"t"},
    {"name":"name1","waitTime":"0","type":"id","value":"myid","NextPage":"np","showMode":"mode","defaultValue":"dvalue","textContent":"t"},
    {"name":"name1","waitTime":"0","type":"id","value":"myid","NextPage":"np","showMode":"mode","defaultValue":"dvalue","textContent":"t"},
    {"name":"name1","waitTime":"0","type":"id","value":"myid","NextPage":"np","showMode":"mode","defaultValue":"dvalue","textContent":"t"},
    {"name":"name1","waitTime":"0","type":"id","value":"myid","NextPage":"np","showMode":"mode","defaultValue":"dvalue","textContent":"t"},
    {"name":"name1","waitTime":"0","type":"id","value":"myid","NextPage":"np","showMode":"mode","defaultValue":"dvalue","textContent":"t"},
    {"name":"name1","waitTime":"0","type":"id","value":"myid","NextPage":"np","showMode":"mode","defaultValue":"dvalue","textContent":"t"},
    {"name":"name1","waitTime":"0","type":"id","value":"myid","NextPage":"np","showMode":"mode","defaultValue":"dvalue","textContent":"t"},
    {"name":"name1","waitTime":"0","type":"id","value":"myid","NextPage":"np","showMode":"mode","defaultValue":"dvalue","textContent":"t"},
    {"name":"name1","waitTime":"0","type":"id","value":"myid","NextPage":"np","showMode":"mode","defaultValue":"dvalue","textContent":"t"},
    {"name":"name1","waitTime":"0","type":"id","value":"myid","NextPage":"np","showMode":"mode","defaultValue":"dvalue","textContent":"t"},
    {"name":"name1","waitTime":"0","type":"id","value":"myid","NextPage":"np","showMode":"mode","defaultValue":"dvalue","textContent":"t"},
    {"name":"name1","waitTime":"0","type":"id","value":"myid","NextPage":"np","showMode":"mode","defaultValue":"dvalue","textContent":"t"},
    {"name":"name1","waitTime":"0","type":"id","value":"myid","NextPage":"np","showMode":"mode","defaultValue":"dvalue","textContent":"t"},
    {"name":"name1","waitTime":"0","type":"id","value":"myid","NextPage":"np","showMode":"mode","defaultValue":"dvalue","textContent":"t"},
    {"name":"name1","waitTime":"0","type":"id","value":"myid","NextPage":"np","showMode":"mode","defaultValue":"dvalue","textContent":"t"},
    {"name":"name1","waitTime":"0","type":"id","value":"myid","NextPage":"np","showMode":"mode","defaultValue":"dvalue","textContent":"t"},
    {"name":"name1","waitTime":"0","type":"id","value":"myid","NextPage":"np","showMode":"mode","defaultValue":"dvalue","textContent":"t"},
    {"name":"name1","waitTime":"0","type":"id","value":"myid","NextPage":"np","showMode":"mode","defaultValue":"dvalue","textContent":"t"},
    {"name":"name1","waitTime":"0","type":"id","value":"myid","NextPage":"np","showMode":"mode","defaultValue":"dvalue","textContent":"t"},
    {"name":"name1","waitTime":"0","type":"id","value":"myid","NextPage":"np","showMode":"mode","defaultValue":"dvalue","textContent":"t"},
    {"name":"name1","waitTime":"0","type":"id","value":"myid","NextPage":"np","showMode":"mode","defaultValue":"dvalue","textContent":"t"},
    {"name":"name1","waitTime":"0","type":"id","value":"myid","NextPage":"np","showMode":"mode","defaultValue":"dvalue","textContent":"t"},
    {"name":"name1","waitTime":"0","type":"id","value":"myid","NextPage":"np","showMode":"mode","defaultValue":"dvalue","textContent":"t"},
    {"name":"name1","waitTime":"0","type":"id","value":"myid","NextPage":"np","showMode":"mode","defaultValue":"dvalue","textContent":"t"},
    {"name":"name1","waitTime":"0","type":"id","value":"myid","NextPage":"np","showMode":"mode","defaultValue":"dvalue","textContent":"t"},
    {"name":"name1","waitTime":"0","type":"id","value":"myid","NextPage":"np","showMode":"mode","defaultValue":"dvalue","textContent":"t"},
    {"name":"name1","waitTime":"0","type":"id","value":"myid","NextPage":"np","showMode":"mode","defaultValue":"dvalue","textContent":"t"},
    {"name":"name1","waitTime":"0","type":"id","value":"myid","NextPage":"np","showMode":"mode","defaultValue":"dvalue","textContent":"t"},
    {"name":"name1","waitTime":"0","type":"id","value":"myid","NextPage":"np","showMode":"mode","defaultValue":"dvalue","textContent":"t"},
    {"name":"name1","waitTime":"0","type":"id","value":"myid","NextPage":"np","showMode":"mode","defaultValue":"dvalue","textContent":"t"},
    {"name":"name1","waitTime":"0","type":"id","value":"myid","NextPage":"np","showMode":"mode","defaultValue":"dvalue","textContent":"t"},
    {"name":"name1","waitTime":"0","type":"id","value":"myid","NextPage":"np","showMode":"mode","defaultValue":"dvalue","textContent":"t"},
    {"name":"name1","waitTime":"0","type":"id","value":"myid","NextPage":"np","showMode":"mode","defaultValue":"dvalue","textContent":"t"},
    {"name":"name1","waitTime":"0","type":"id","value":"myid","NextPage":"np","showMode":"mode","defaultValue":"dvalue","textContent":"t"},
    {"name":"name1","waitTime":"0","type":"id","value":"myid","NextPage":"np","showMode":"mode","defaultValue":"dvalue","textContent":"t"},
    {"name":"name1","waitTime":"0","type":"id","value":"myid","NextPage":"np","showMode":"mode","defaultValue":"dvalue","textContent":"t"},
    {"name":"name1","waitTime":"0","type":"id","value":"myid","NextPage":"np","showMode":"mode","defaultValue":"dvalue","textContent":"t"},
    {"name":"name1","waitTime":"0","type":"id","value":"myid","NextPage":"np","showMode":"mode","defaultValue":"dvalue","textContent":"t"},
    {"name":"name1","waitTime":"0","type":"id","value":"myid","NextPage":"np","showMode":"mode","defaultValue":"dvalue","textContent":"t"},
    {"name":"name1","waitTime":"0","type":"id","value":"myid","NextPage":"np","showMode":"mode","defaultValue":"dvalue","textContent":"t"},
    {"name":"name1","waitTime":"0","type":"id","value":"myid","NextPage":"np","showMode":"mode","defaultValue":"dvalue","textContent":"t"},
    {"name":"name1","waitTime":"0","type":"id","value":"myid","NextPage":"np","showMode":"mode","defaultValue":"dvalue","textContent":"t"},
    {"name":"name1","waitTime":"0","type":"id","value":"myid","NextPage":"np","showMode":"mode","defaultValue":"dvalue","textContent":"t"},
    {"name":"name1","waitTime":"0","type":"id","value":"myid","NextPage":"np","showMode":"mode","defaultValue":"dvalue","textContent":"t"},
    {"name":"name1","waitTime":"0","type":"id","value":"myid","NextPage":"np","showMode":"mode","defaultValue":"dvalue","textContent":"t"},
    {"name":"name1","waitTime":"0","type":"id","value":"myid","NextPage":"np","showMode":"mode","defaultValue":"dvalue","textContent":"t"},
    {"name":"name1","waitTime":"0","type":"id","value":"myid","NextPage":"np","showMode":"mode","defaultValue":"dvalue","textContent":"t"},
    {"name":"name1","waitTime":"0","type":"id","value":"myid","NextPage":"np","showMode":"mode","defaultValue":"dvalue","textContent":"t"},
    {"name":"name1","waitTime":"0","type":"id","value":"myid","NextPage":"np","showMode":"mode","defaultValue":"dvalue","textContent":"t"},
    {"name":"name1","waitTime":"0","type":"id","value":"myid","NextPage":"np","showMode":"mode","defaultValue":"dvalue","textContent":"t"},
    {"name":"name1","waitTime":"0","type":"id","value":"myid","NextPage":"np","showMode":"mode","defaultValue":"dvalue","textContent":"t"},
    {"name":"name1","waitTime":"0","type":"id","value":"myid","NextPage":"np","showMode":"mode","defaultValue":"dvalue","textContent":"t"},
    {"name":"name1","waitTime":"0","type":"id","value":"myid","NextPage":"np","showMode":"mode","defaultValue":"dvalue","textContent":"t"},
    {"name":"name1","waitTime":"0","type":"id","value":"myid","NextPage":"np","showMode":"mode","defaultValue":"dvalue","textContent":"t"},
    {"name":"name1","waitTime":"0","type":"id","value":"myid","NextPage":"np","showMode":"mode","defaultValue":"dvalue","textContent":"t"},
    {"name":"name1","waitTime":"0","type":"id","value":"myid","NextPage":"np","showMode":"mode","defaultValue":"dvalue","textContent":"t"},
    {"name":"name1","waitTime":"0","type":"id","value":"myid","NextPage":"np","showMode":"mode","defaultValue":"dvalue","textContent":"t"},
    {"name":"name1","waitTime":"0","type":"id","value":"myid","NextPage":"np","showMode":"mode","defaultValue":"dvalue","textContent":"t"},
    {"name":"name1","waitTime":"0","type":"id","value":"myid","NextPage":"np","showMode":"mode","defaultValue":"dvalue","textContent":"t"},
    {"name":"name1","waitTime":"0","type":"id","value":"myid","NextPage":"np","showMode":"mode","defaultValue":"dvalue","textContent":"t"},
    {"name":"name1","waitTime":"0","type":"id","value":"myid","NextPage":"np","showMode":"mode","defaultValue":"dvalue","textContent":"t"},
    {"name":"name1","waitTime":"0","type":"id","value":"myid","NextPage":"np","showMode":"mode","defaultValue":"dvalue","textContent":"t"},
    {"name":"name1","waitTime":"0","type":"id","value":"myid","NextPage":"np","showMode":"mode","defaultValue":"dvalue","textContent":"t"},
    {"name":"name1","waitTime":"0","type":"id","value":"myid","NextPage":"np","showMode":"mode","defaultValue":"dvalue","textContent":"t"},
    {"name":"name1","waitTime":"0","type":"id","value":"myid","NextPage":"np","showMode":"mode","defaultValue":"dvalue","textContent":"t"},
    {"name":"name1","waitTime":"0","type":"id","value":"myid","NextPage":"np","showMode":"mode","defaultValue":"dvalue","textContent":"t"},
    {"name":"name1","waitTime":"0","type":"id","value":"myid","NextPage":"np","showMode":"mode","defaultValue":"dvalue","textContent":"t"},
    {"name":"name1","waitTime":"0","type":"id","value":"myid","NextPage":"np","showMode":"mode","defaultValue":"dvalue","textContent":"t"},
    {"name":"name1","waitTime":"0","type":"id","value":"myid","NextPage":"np","showMode":"mode","defaultValue":"dvalue","textContent":"t"},
    {"name":"name1","waitTime":"0","type":"id","value":"myid","NextPage":"np","showMode":"mode","defaultValue":"dvalue","textContent":"t"},
    {"name":"name1","waitTime":"0","type":"id","value":"myid","NextPage":"np","showMode":"mode","defaultValue":"dvalue","textContent":"t"},
    {"name":"name1","waitTime":"0","type":"id","value":"myid","NextPage":"np","showMode":"mode","defaultValue":"dvalue","textContent":"t"},
    {"name":"name1","waitTime":"0","type":"id","value":"myid","NextPage":"np","showMode":"mode","defaultValue":"dvalue","textContent":"t"},
    {"name":"name1","waitTime":"0","type":"id","value":"myid","NextPage":"np","showMode":"mode","defaultValue":"dvalue","textContent":"t"},
    {"name":"name1","waitTime":"0","type":"id","value":"myid","NextPage":"np","showMode":"mode","defaultValue":"dvalue","textContent":"t"},
    {"name":"name1","waitTime":"0","type":"id","value":"myid","NextPage":"np","showMode":"mode","defaultValue":"dvalue","textContent":"t"},
    {"name":"name1","waitTime":"0","type":"id","value":"myid","NextPage":"np","showMode":"mode","defaultValue":"dvalue","textContent":"t"},
    {"name":"name1","waitTime":"0","type":"id","value":"myid","NextPage":"np","showMode":"mode","defaultValue":"dvalue","textContent":"t"},
    {"name":"name1","waitTime":"0","type":"id","value":"myid","NextPage":"np","showMode":"mode","defaultValue":"dvalue","textContent":"t"},
    {"name":"name1","waitTime":"0","type":"id","value":"myid","NextPage":"np","showMode":"mode","defaultValue":"dvalue","textContent":"t"},
    {"name":"name1","waitTime":"0","type":"id","value":"myid","NextPage":"np","showMode":"mode","defaultValue":"dvalue","textContent":"t"},
    {"name":"name1","waitTime":"0","type":"id","value":"myid","NextPage":"np","showMode":"mode","defaultValue":"dvalue","textContent":"t"},
    {"name":"name1","waitTime":"0","type":"id","value":"myid","NextPage":"np","showMode":"mode","defaultValue":"dvalue","textContent":"t"},
    {"name":"name1","waitTime":"0","type":"id","value":"myid","NextPage":"np","showMode":"mode","defaultValue":"dvalue","textContent":"t"},
    {"name":"name1","waitTime":"0","type":"id","value":"myid","NextPage":"np","showMode":"mode","defaultValue":"dvalue","textContent":"t"},
    {"name":"name1","waitTime":"0","type":"id","value":"myid","NextPage":"np","showMode":"mode","defaultValue":"dvalue","textContent":"t"},
    {"name":"name1","waitTime":"0","type":"id","value":"myid","NextPage":"np","showMode":"mode","defaultValue":"dvalue","textContent":"t"},
    {"name":"name1","waitTime":"0","type":"id","value":"myid","NextPage":"np","showMode":"mode","defaultValue":"dvalue","textContent":"t"},
    {"name":"name1","waitTime":"0","type":"id","value":"myid","NextPage":"np","showMode":"mode","defaultValue":"dvalue","textContent":"t"},
    {"name":"name1","waitTime":"0","type":"id","value":"myid","NextPage":"np","showMode":"mode","defaultValue":"dvalue","textContent":"t"},
    {"name":"name1","waitTime":"0","type":"id","value":"myid","NextPage":"np","showMode":"mode","defaultValue":"dvalue","textContent":"t"},
    {"name":"name1","waitTime":"0","type":"id","value":"myid","NextPage":"np","showMode":"mode","defaultValue":"dvalue","textContent":"t"},
    {"name":"name1","waitTime":"0","type":"id","value":"myid","NextPage":"np","showMode":"mode","defaultValue":"dvalue","textContent":"t"},
    {"name":"name1","waitTime":"0","type":"id","value":"myid","NextPage":"np","showMode":"mode","defaultValue":"dvalue","textContent":"t"},
    {"name":"name1","waitTime":"0","type":"id","value":"myid","NextPage":"np","showMode":"mode","defaultValue":"dvalue","textContent":"t"},
    {"name":"name1","waitTime":"0","type":"id","value":"myid","NextPage":"np","showMode":"mode","defaultValue":"dvalue","textContent":"t"},
    {"name":"name1","waitTime":"0","type":"id","value":"myid","NextPage":"np","showMode":"mode","defaultValue":"dvalue","textContent":"t"},
    {"name":"name1","waitTime":"0","type":"id","value":"myid","NextPage":"np","showMode":"mode","defaultValue":"dvalue","textContent":"t"},
    {"name":"name1","waitTime":"0","type":"id","value":"myid","NextPage":"np","showMode":"mode","defaultValue":"dvalue","textContent":"t"},
    {"name":"name1","waitTime":"0","type":"id","value":"myid","NextPage":"np","showMode":"mode","defaultValue":"dvalue","textContent":"t"},
    {"name":"name1","waitTime":"0","type":"id","value":"myid","NextPage":"np","showMode":"mode","defaultValue":"dvalue","textContent":"t"},
    {"name":"name1","waitTime":"0","type":"id","value":"myid","NextPage":"np","showMode":"mode","defaultValue":"dvalue","textContent":"t"},
    {"name":"name1","waitTime":"0","type":"id","value":"myid","NextPage":"np","showMode":"mode","defaultValue":"dvalue","textContent":"t"},
    {"name":"name1","waitTime":"0","type":"id","value":"myid","NextPage":"np","showMode":"mode","defaultValue":"dvalue","textContent":"t"},
    {"name":"name1","waitTime":"0","type":"id","value":"myid","NextPage":"np","showMode":"mode","defaultValue":"dvalue","textContent":"t"},
    {"name":"name1","waitTime":"0","type":"id","value":"myid","NextPage":"np","showMode":"mode","defaultValue":"dvalue","textContent":"t"},
    {"name":"name1","waitTime":"0","type":"id","value":"myid","NextPage":"np","showMode":"mode","defaultValue":"dvalue","textContent":"t"},
    {"name":"name1","waitTime":"0","type":"id","value":"myid","NextPage":"np","showMode":"mode","defaultValue":"dvalue","textContent":"t"},
    {"name":"name1","waitTime":"0","type":"id","value":"myid","NextPage":"np","showMode":"mode","defaultValue":"dvalue","textContent":"t"},
    {"name":"name1","waitTime":"0","type":"id","value":"myid","NextPage":"np","showMode":"mode","defaultValue":"dvalue","textContent":"t"},
    {"name":"name1","waitTime":"0","type":"id","value":"myid","NextPage":"np","showMode":"mode","defaultValue":"dvalue","textContent":"t"},
    {"name":"name1","waitTime":"0","type":"id","value":"myid","NextPage":"np","showMode":"mode","defaultValue":"dvalue","textContent":"t"},
    {"name":"name1","waitTime":"0","type":"id","value":"myid","NextPage":"np","showMode":"mode","defaultValue":"dvalue","textContent":"t"},
    {"name":"name1","waitTime":"0","type":"id","value":"myid","NextPage":"np","showMode":"mode","defaultValue":"dvalue","textContent":"t"},
    {"name":"name1","waitTime":"0","type":"id","value":"myid","NextPage":"np","showMode":"mode","defaultValue":"dvalue","textContent":"t"},
    {"name":"name1","waitTime":"0","type":"id","value":"myid","NextPage":"np","showMode":"mode","defaultValue":"dvalue","textContent":"t"},
    {"name":"name1","waitTime":"0","type":"id","value":"myid","NextPage":"np","showMode":"mode","defaultValue":"dvalue","textContent":"t"},
    {"name":"name1","waitTime":"0","type":"id","value":"myid","NextPage":"np","showMode":"mode","defaultValue":"dvalue","textContent":"t"},
    {"name":"name1","waitTime":"0","type":"id","value":"myid","NextPage":"np","showMode":"mode","defaultValue":"dvalue","textContent":"t"},
    {"name":"name1","waitTime":"0","type":"id","value":"myid","NextPage":"np","showMode":"mode","defaultValue":"dvalue","textContent":"t"},
    {"name":"name1","waitTime":"0","type":"id","value":"myid","NextPage":"np","showMode":"mode","defaultValue":"dvalue","textContent":"t"},
    {"name":"name1","waitTime":"0","type":"id","value":"myid","NextPage":"np","showMode":"mode","defaultValue":"dvalue","textContent":"t"},
    {"name":"name1","waitTime":"0","type":"id","value":"myid","NextPage":"np","showMode":"mode","defaultValue":"dvalue","textContent":"t"},
    {"name":"name1","waitTime":"0","type":"id","value":"myid","NextPage":"np","showMode":"mode","defaultValue":"dvalue","textContent":"t"},
    {"name":"name1","waitTime":"0","type":"id","value":"myid","NextPage":"np","showMode":"mode","defaultValue":"dvalue","textContent":"t"},
    {"name":"name1","waitTime":"0","type":"id","value":"myid","NextPage":"np","showMode":"mode","defaultValue":"dvalue","textContent":"t"},
    {"name":"name1","waitTime":"0","type":"id","value":"myid","NextPage":"np","showMode":"mode","defaultValue":"dvalue","textContent":"t"},
    {"name":"name1","waitTime":"0","type":"id","value":"myid","NextPage":"np","showMode":"mode","defaultValue":"dvalue","textContent":"t"},
    {"name":"name1","waitTime":"0","type":"id","value":"myid","NextPage":"np","showMode":"mode","defaultValue":"dvalue","textContent":"t"},
    {"name":"name1","waitTime":"0","type":"id","value":"myid","NextPage":"np","showMode":"mode","defaultValue":"dvalue","textContent":"t"},
    {"name":"name1","waitTime":"0","type":"id","value":"myid","NextPage":"np","showMode":"mode","defaultValue":"dvalue","textContent":"t"},
    {"name":"name1","waitTime":"0","type":"id","value":"myid","NextPage":"np","showMode":"mode","defaultValue":"dvalue","textContent":"t"},
    {"name":"name1","waitTime":"0","type":"id","value":"myid","NextPage":"np","showMode":"mode","defaultValue":"dvalue","textContent":"t"},
    {"name":"name1","waitTime":"0","type":"id","value":"myid","NextPage":"np","showMode":"mode","defaultValue":"dvalue","textContent":"t"},
    {"name":"name1","waitTime":"0","type":"id","value":"myid","NextPage":"np","showMode":"mode","defaultValue":"dvalue","textContent":"t"},
    {"name":"name1","waitTime":"0","type":"id","value":"myid","NextPage":"np","showMode":"mode","defaultValue":"dvalue","textContent":"t"},
    {"name":"name1","waitTime":"0","type":"id","value":"myid","NextPage":"np","showMode":"mode","defaultValue":"dvalue","textContent":"t"},
    {"name":"name1","waitTime":"0","type":"id","value":"myid","NextPage":"np","showMode":"mode","defaultValue":"dvalue","textContent":"t"},
    {"name":"name1","waitTime":"0","type":"id","value":"myid","NextPage":"np","showMode":"mode","defaultValue":"dvalue","textContent":"t"},
    {"name":"name1","waitTime":"0","type":"id","value":"myid","NextPage":"np","showMode":"mode","defaultValue":"dvalue","textContent":"t"},
    {"name":"name1","waitTime":"0","type":"id","value":"myid","NextPage":"np","showMode":"mode","defaultValue":"dvalue","textContent":"t"},
    {"name":"name1","waitTime":"0","type":"id","value":"myid","NextPage":"np","showMode":"mode","defaultValue":"dvalue","textContent":"t"},
    {"name":"name1","waitTime":"0","type":"id","value":"myid","NextPage":"np","showMode":"mode","defaultValue":"dvalue","textContent":"t"},
    {"name":"name1","waitTime":"0","type":"id","value":"myid","NextPage":"np","showMode":"mode","defaultValue":"dvalue","textContent":"t"},
    {"name":"name1","waitTime":"0","type":"id","value":"myid","NextPage":"np","showMode":"mode","defaultValue":"dvalue","textContent":"t"},
    {"name":"name1","waitTime":"0","type":"id","value":"myid","NextPage":"np","showMode":"mode","defaultValue":"dvalue","textContent":"t"},
    {"name":"name1","waitTime":"0","type":"id","value":"myid","NextPage":"np","showMode":"mode","defaultValue":"dvalue","textContent":"t"},
    {"name":"name1","waitTime":"0","type":"id","value":"myid","NextPage":"np","showMode":"mode","defaultValue":"dvalue","textContent":"t"},
    {"name":"name1","waitTime":"0","type":"id","value":"myid","NextPage":"np","showMode":"mode","defaultValue":"dvalue","textContent":"t"},
    {"name":"name1","waitTime":"0","type":"id","value":"myid","NextPage":"np","showMode":"mode","defaultValue":"dvalue","textContent":"t"},
    {"name":"name1","waitTime":"0","type":"id","value":"myid","NextPage":"np","showMode":"mode","defaultValue":"dvalue","textContent":"t"},
    {"name":"name1","waitTime":"0","type":"id","value":"myid","NextPage":"np","showMode":"mode","defaultValue":"dvalue","textContent":"t"},
    {"name":"name1","waitTime":"0","type":"id","value":"myid","NextPage":"np","showMode":"mode","defaultValue":"dvalue","textContent":"t"},
    {"name":"name1","waitTime":"0","type":"id","value":"myid","NextPage":"np","showMode":"mode","defaultValue":"dvalue","textContent":"t"},
    {"name":"name1","waitTime":"0","type":"id","value":"myid","NextPage":"np","showMode":"mode","defaultValue":"dvalue","textContent":"t"},
    {"name":"name1","waitTime":"0","type":"id","value":"myid","NextPage":"np","showMode":"mode","defaultValue":"dvalue","textContent":"t"},
    {"name":"name1","waitTime":"0","type":"id","value":"myid","NextPage":"np","showMode":"mode","defaultValue":"dvalue","textContent":"t"},
    {"name":"name1","waitTime":"0","type":"id","value":"myid","NextPage":"np","showMode":"mode","defaultValue":"dvalue","textContent":"t"},
    {"name":"name1","waitTime":"0","type":"id","value":"myid","NextPage":"np","showMode":"mode","defaultValue":"dvalue","textContent":"t"},
    {"name":"name1","waitTime":"0","type":"id","value":"myid","NextPage":"np","showMode":"mode","defaultValue":"dvalue","textContent":"t"},
    {"name":"name1","waitTime":"0","type":"id","value":"myid","NextPage":"np","showMode":"mode","defaultValue":"dvalue","textContent":"t"},
    {"name":"name1","waitTime":"0","type":"id","value":"myid","NextPage":"np","showMode":"mode","defaultValue":"dvalue","textContent":"t"},
    {"name":"name1","waitTime":"0","type":"id","value":"myid","NextPage":"np","showMode":"mode","defaultValue":"dvalue","textContent":"t"},
    {"name":"name1","waitTime":"0","type":"id","value":"myid","NextPage":"np","showMode":"mode","defaultValue":"dvalue","textContent":"t"},
    {"name":"name1","waitTime":"0","type":"id","value":"myid","NextPage":"np","showMode":"mode","defaultValue":"dvalue","textContent":"t"},
    {"name":"name1","waitTime":"0","type":"id","value":"myid","NextPage":"np","showMode":"mode","defaultValue":"dvalue","textContent":"t"},
    {"name":"name1","waitTime":"0","type":"id","value":"myid","NextPage":"np","showMode":"mode","defaultValue":"dvalue","textContent":"t"},
    {"name":"name1","waitTime":"0","type":"id","value":"myid","NextPage":"np","showMode":"mode","defaultValue":"dvalue","textContent":"t"},
    {"name":"name1","waitTime":"0","type":"id","value":"myid","NextPage":"np","showMode":"mode","defaultValue":"dvalue","textContent":"t"},
    {"name":"name1","waitTime":"0","type":"id","value":"myid","NextPage":"np","showMode":"mode","defaultValue":"dvalue","textContent":"t"},
    {"name":"name1","waitTime":"0","type":"id","value":"myid","NextPage":"np","showMode":"mode","defaultValue":"dvalue","textContent":"t"},
    {"name":"name1","waitTime":"0","type":"id","value":"myid","NextPage":"np","showMode":"mode","defaultValue":"dvalue","textContent":"t"},
    {"name":"name1","waitTime":"0","type":"id","value":"myid","NextPage":"np","showMode":"mode","defaultValue":"dvalue","textContent":"t"},
    {"name":"name1","waitTime":"0","type":"id","value":"myid","NextPage":"np","showMode":"mode","defaultValue":"dvalue","textContent":"t"},
    {"name":"name1","waitTime":"0","type":"id","value":"myid","NextPage":"np","showMode":"mode","defaultValue":"dvalue","textContent":"t"},
    {"name":"name1","waitTime":"0","type":"id","value":"myid","NextPage":"np","showMode":"mode","defaultValue":"dvalue","textContent":"t"},
    {"name":"name1","waitTime":"0","type":"id","value":"myid","NextPage":"np","showMode":"mode","defaultValue":"dvalue","textContent":"t"},
    {"name":"name1","waitTime":"0","type":"id","value":"myid","NextPage":"np","showMode":"mode","defaultValue":"dvalue","textContent":"t"},
    {"name":"name1","waitTime":"0","type":"id","value":"myid","NextPage":"np","showMode":"mode","defaultValue":"dvalue","textContent":"t"},
    {"name":"name1","waitTime":"0","type":"id","value":"myid","NextPage":"np","showMode":"mode","defaultValue":"dvalue","textContent":"t"},
    {"name":"name1","waitTime":"0","type":"id","value":"myid","NextPage":"np","showMode":"mode","defaultValue":"dvalue","textContent":"t"},
    {"name":"name1","waitTime":"0","type":"id","value":"myid","NextPage":"np","showMode":"mode","defaultValue":"dvalue","textContent":"t"},
    {"name":"name1","waitTime":"0","type":"id","value":"myid","NextPage":"np","showMode":"mode","defaultValue":"dvalue","textContent":"t"},
    {"name":"name1","waitTime":"0","type":"id","value":"myid","NextPage":"np","showMode":"mode","defaultValue":"dvalue","textContent":"t"},
    {"name":"name1","waitTime":"0","type":"id","value":"myid","NextPage":"np","showMode":"mode","defaultValue":"dvalue","textContent":"t"},
    {"name":"name1","waitTime":"0","type":"id","value":"myid","NextPage":"np","showMode":"mode","defaultValue":"dvalue","textContent":"t"},
    {"name":"name1","waitTime":"0","type":"id","value":"myid","NextPage":"np","showMode":"mode","defaultValue":"dvalue","textContent":"t"},
    {"name":"name1","waitTime":"0","type":"id","value":"myid","NextPage":"np","showMode":"mode","defaultValue":"dvalue","textContent":"t"},
    {"name":"name1","waitTime":"0","type":"id","value":"myid","NextPage":"np","showMode":"mode","defaultValue":"dvalue","textContent":"t"},
    {"name":"name1","waitTime":"0","type":"id","value":"myid","NextPage":"np","showMode":"mode","defaultValue":"dvalue","textContent":"t"},
    {"name":"name1","waitTime":"0","type":"id","value":"myid","NextPage":"np","showMode":"mode","defaultValue":"dvalue","textContent":"t"},
    {"name":"name1","waitTime":"0","type":"id","value":"myid","NextPage":"np","showMode":"mode","defaultValue":"dvalue","textContent":"t"},
    {"name":"name1","waitTime":"0","type":"id","value":"myid","NextPage":"np","showMode":"mode","defaultValue":"dvalue","textContent":"t"},
    {"name":"name1","waitTime":"0","type":"id","value":"myid","NextPage":"np","showMode":"mode","defaultValue":"dvalue","textContent":"t"},
    {"name":"name1","waitTime":"0","type":"id","value":"myid","NextPage":"np","showMode":"mode","defaultValue":"dvalue","textContent":"t"},
    {"name":"name1","waitTime":"0","type":"id","value":"myid","NextPage":"np","showMode":"mode","defaultValue":"dvalue","textContent":"t"},
    {"name":"name1","waitTime":"0","type":"id","value":"myid","NextPage":"np","showMode":"mode","defaultValue":"dvalue","textContent":"t"},
    {"name":"name1","waitTime":"0","type":"id","value":"myid","NextPage":"np","showMode":"mode","defaultValue":"dvalue","textContent":"t"},
    {"name":"name1","waitTime":"0","type":"id","value":"myid","NextPage":"np","showMode":"mode","defaultValue":"dvalue","textContent":"t"},
    {"name":"name1","waitTime":"0","type":"id","value":"myid","NextPage":"np","showMode":"mode","defaultValue":"dvalue","textContent":"t"},
    {"name":"name1","waitTime":"0","type":"id","value":"myid","NextPage":"np","showMode":"mode","defaultValue":"dvalue","textContent":"t"},
    {"name":"name1","waitTime":"0","type":"id","value":"myid","NextPage":"np","showMode":"mode","defaultValue":"dvalue","textContent":"t"},
    {"name":"name1","waitTime":"0","type":"id","value":"myid","NextPage":"np","showMode":"mode","defaultValue":"dvalue","textContent":"t"},
    {"name":"name1","waitTime":"0","type":"id","value":"myid","NextPage":"np","showMode":"mode","defaultValue":"dvalue","textContent":"t"},
    {"name":"name1","waitTime":"0","type":"id","value":"myid","NextPage":"np","showMode":"mode","defaultValue":"dvalue","textContent":"t"},
    {"name":"name1","waitTime":"0","type":"id","value":"myid","NextPage":"np","showMode":"mode","defaultValue":"dvalue","textContent":"t"},
    {"name":"name1","waitTime":"0","type":"id","value":"myid","NextPage":"np","showMode":"mode","defaultValue":"dvalue","textContent":"t"},
    {"name":"name1","waitTime":"0","type":"id","value":"myid","NextPage":"np","showMode":"mode","defaultValue":"dvalue","textContent":"t"},
    {"name":"name1","waitTime":"0","type":"id","value":"myid","NextPage":"np","showMode":"mode","defaultValue":"dvalue","textContent":"t"},
    {"name":"name1","waitTime":"0","type":"id","value":"myid","NextPage":"np","showMode":"mode","defaultValue":"dvalue","textContent":"t"},
    {"name":"name1","waitTime":"0","type":"id","value":"myid","NextPage":"np","showMode":"mode","defaultValue":"dvalue","textContent":"t"},
    {"name":"name1","waitTime":"0","type":"id","value":"myid","NextPage":"np","showMode":"mode","defaultValue":"dvalue","textContent":"t"},
    {"name":"name1","waitTime":"0","type":"id","value":"myid","NextPage":"np","showMode":"mode","defaultValue":"dvalue","textContent":"t"},
    {"name":"name1","waitTime":"0","type":"id","value":"myid","NextPage":"np","showMode":"mode","defaultValue":"dvalue","textContent":"t"},
    {"name":"name1","waitTime":"0","type":"id","value":"myid","NextPage":"np","showMode":"mode","defaultValue":"dvalue","textContent":"t"},
    {"name":"name1","waitTime":"0","type":"id","value":"myid","NextPage":"np","showMode":"mode","defaultValue":"dvalue","textContent":"t"},
    {"name":"name1","waitTime":"0","type":"id","value":"myid","NextPage":"np","showMode":"mode","defaultValue":"dvalue","textContent":"t"},
    {"name":"name1","waitTime":"0","type":"id","value":"myid","NextPage":"np","showMode":"mode","defaultValue":"dvalue","textContent":"t"},
    {"name":"name1","waitTime":"0","type":"id","value":"myid","NextPage":"np","showMode":"mode","defaultValue":"dvalue","textContent":"t"},
    {"name":"name1","waitTime":"0","type":"id","value":"myid","NextPage":"np","showMode":"mode","defaultValue":"dvalue","textContent":"t"},
    {"name":"name1","waitTime":"0","type":"id","value":"myid","NextPage":"np","showMode":"mode","defaultValue":"dvalue","textContent":"t"},
    {"name":"name1","waitTime":"0","type":"id","value":"myid","NextPage":"np","showMode":"mode","defaultValue":"dvalue","textContent":"t"},
    {"name":"name1","waitTime":"0","type":"id","value":"myid","NextPage":"np","showMode":"mode","defaultValue":"dvalue","textContent":"t"},
    {"name":"name1","waitTime":"0","type":"id","value":"myid","NextPage":"np","showMode":"mode","defaultValue":"dvalue","textContent":"t"},
    {"name":"name1","waitTime":"0","type":"id","value":"myid","NextPage":"np","showMode":"mode","defaultValue":"dvalue","textContent":"t"},
    {"name":"name1","waitTime":"0","type":"id","value":"myid","NextPage":"np","showMode":"mode","defaultValue":"dvalue","textContent":"t"},
    {"name":"name1","waitTime":"0","type":"id","value":"myid","NextPage":"np","showMode":"mode","defaultValue":"dvalue","textContent":"t"},
    {"name":"name1","waitTime":"0","type":"id","value":"myid","NextPage":"np","showMode":"mode","defaultValue":"dvalue","textContent":"t"},
    {"name":"name1","waitTime":"0","type":"id","value":"myid","NextPage":"np","showMode":"mode","defaultValue":"dvalue","textContent":"t"},
    {"name":"name1","waitTime":"0","type":"id","value":"myid","NextPage":"np","showMode":"mode","defaultValue":"dvalue","textContent":"t"},
    {"name":"name1","waitTime":"0","type":"id","value":"myid","NextPage":"np","showMode":"mode","defaultValue":"dvalue","textContent":"t"},
    {"name":"name1","waitTime":"0","type":"id","value":"myid","NextPage":"np","showMode":"mode","defaultValue":"dvalue","textContent":"t"},
    {"name":"name1","waitTime":"0","type":"id","value":"myid","NextPage":"np","showMode":"mode","defaultValue":"dvalue","textContent":"t"},
    {"name":"name1","waitTime":"0","type":"id","value":"myid","NextPage":"np","showMode":"mode","defaultValue":"dvalue","textContent":"t"},
    {"name":"name1","waitTime":"0","type":"id","value":"myid","NextPage":"np","showMode":"mode","defaultValue":"dvalue","textContent":"t"},
    {"name":"name1","waitTime":"0","type":"id","value":"myid","NextPage":"np","showMode":"mode","defaultValue":"dvalue","textContent":"t"},
    {"name":"name1","waitTime":"0","type":"id","value":"myid","NextPage":"np","showMode":"mode","defaultValue":"dvalue","textContent":"t"},
    {"name":"name1","waitTime":"0","type":"id","value":"myid","NextPage":"np","showMode":"mode","defaultValue":"dvalue","textContent":"t"},
    {"name":"name1","waitTime":"0","type":"id","value":"myid","NextPage":"np","showMode":"mode","defaultValue":"dvalue","textContent":"t"},
    {"name":"name1","waitTime":"0","type":"id","value":"myid","NextPage":"np","showMode":"mode","defaultValue":"dvalue","textContent":"t"},
    {"name":"name1","waitTime":"0","type":"id","value":"myid","NextPage":"np","showMode":"mode","defaultValue":"dvalue","textContent":"t"},
    {"name":"name1","waitTime":"0","type":"id","value":"myid","NextPage":"np","showMode":"mode","defaultValue":"dvalue","textContent":"t"},
    {"name":"name1","waitTime":"0","type":"id","value":"myid","NextPage":"np","showMode":"mode","defaultValue":"dvalue","textContent":"t"},
    {"name":"name1","waitTime":"0","type":"id","value":"myid","NextPage":"np","showMode":"mode","defaultValue":"dvalue","textContent":"t"},
    {"name":"name1","waitTime":"0","type":"id","value":"myid","NextPage":"np","showMode":"mode","defaultValue":"dvalue","textContent":"t"},
    {"name":"name1","waitTime":"0","type":"id","value":"myid","NextPage":"np","showMode":"mode","defaultValue":"dvalue","textContent":"t"},
    {"name":"name1","waitTime":"0","type":"id","value":"myid","NextPage":"np","showMode":"mode","defaultValue":"dvalue","textContent":"t"},
    {"name":"name1","waitTime":"0","type":"id","value":"myid","NextPage":"np","showMode":"mode","defaultValue":"dvalue","textContent":"t"},
    {"name":"name1","waitTime":"0","type":"id","value":"myid","NextPage":"np","showMode":"mode","defaultValue":"dvalue","textContent":"t"},
    {"name":"name1","waitTime":"0","type":"id","value":"myid","NextPage":"np","showMode":"mode","defaultValue":"dvalue","textContent":"t"},
    {"name":"name1","waitTime":"0","type":"id","value":"myid","NextPage":"np","showMode":"mode","defaultValue":"dvalue","textContent":"t"},
    {"name":"name1","waitTime":"0","type":"id","value":"myid","NextPage":"np","showMode":"mode","defaultValue":"dvalue","textContent":"t"},
    {"name":"name1","waitTime":"0","type":"id","value":"myid","NextPage":"np","showMode":"mode","defaultValue":"dvalue","textContent":"t"},
    {"name":"name1","waitTime":"0","type":"id","value":"myid","NextPage":"np","showMode":"mode","defaultValue":"dvalue","textContent":"t"},
    {"name":"name1","waitTime":"0","type":"id","value":"myid","NextPage":"np","showMode":"mode","defaultValue":"dvalue","textContent":"t"},
    {"name":"name1","waitTime":"0","type":"id","value":"myid","NextPage":"np","showMode":"mode","defaultValue":"dvalue","textContent":"t"},
    {"name":"name1","waitTime":"0","type":"id","value":"myid","NextPage":"np","showMode":"mode","defaultValue":"dvalue","textContent":"t"},
    {"name":"name1","waitTime":"0","type":"id","value":"myid","NextPage":"np","showMode":"mode","defaultValue":"dvalue","textContent":"t"},
    {"name":"name1","waitTime":"0","type":"id","value":"myid","NextPage":"np","showMode":"mode","defaultValue":"dvalue","textContent":"t"}
  ],
  "pop":true
}